code/__init__.py
code/models/__init__.py
code/models/books.py
code/ticker_streamer/__init__.py
code/ticker_streamer/__main__.py
code/ticker_streamer/main.py
entities/__init__.py
entities/entities.py
exceptions/__init__.py
exceptions/exceptions.py
exchange/__init__.py
exchange/exchange.py
main/__init__.py
main/__main__-SCOTT-2C610FV.py
main/__main__.py
main/main_system.py
main/__pycache__/__main__.cpython-38.pyc
models/__init__.py
models/books.py
models/dual_heap.py
models/error_event.py
models/main_system.py
models/order.py
models/positions_manager.py
models/strategy.py
models/subscription_event.py
models/transaction.py
position_management/__init__.py
position_management/exchange.py
position_management/position_manager.py
position_management/positions_manager.py
position_management/test_puller.py
prototrade/__init__.py
prototrade/__main__.py
prototrade/error_processor.py
prototrade/prototrade.py
src/__init__.py
test_strategies/__init__.py
test_strategies/test_strategy_1.py
ticker_streamer/__init__.py
ticker_streamer/__main__.py
ticker_streamer/alpaca_streamer.py
ticker_streamer/main.py
ticker_streamer/price_updater.py
ticker_streamer/subscription_manager.py
ticker_streamer/ticker_streamer.py
prototradeTest-0.0.4.dist-info/METADATA
prototradeTest-0.0.4.dist-info/WHEEL
prototradeTest-0.0.4.dist-info/top_level.txt
prototradeTest-0.0.4.dist-info/RECORD
